setup.py
ngl_utils/__init__.py
ngl_utils/messages.py
ngl_utils/ncodegenerator.py
ngl_utils/ngluic.py
ngl_utils/rle.py
ngl_utils/uiparser.py
ngl_utils.egg-info/PKG-INFO
ngl_utils.egg-info/SOURCES.txt
ngl_utils.egg-info/dependency_links.txt
ngl_utils.egg-info/entry_points.txt
ngl_utils.egg-info/top_level.txt
ngl_utils/nbitmap/__init__.py
ngl_utils/nbitmap/converter.py
ngl_utils/nbitmap/nbitmap.py
ngl_utils/nfont/__init__.py
ngl_utils/nfont/codeview.py
ngl_utils/nfont/consolewidget.py
ngl_utils/nfont/converter.py
ngl_utils/nfont/converterwidget.py
ngl_utils/nfont/cparser.py
ngl_utils/nfont/editwidget.py
ngl_utils/nfont/nfont.py
ngl_utils/nfont/nfonts_rc.py
ngl_utils/nfont/qtres/ngl_font.ui
ngl_utils/nfont/qtres/ngl_font_edit.ui
ngl_utils/nplugins/__init__.py
ngl_utils/nplugins/nplugins.py
ngl_utils/nplugins/python/__init__.py
ngl_utils/nplugins/python/ngl_base_qplugin.py
ngl_utils/nplugins/python/ngl_bitmap_plugin.py
ngl_utils/nplugins/python/ngl_button_plugin.py
ngl_utils/nplugins/python/ngl_checkbox_plugin.py
ngl_utils/nplugins/python/ngl_fillbar_plugin.py
ngl_utils/nplugins/python/ngl_graph_scale_plugin.py
ngl_utils/nplugins/python/ngl_label_plugin.py
ngl_utils/nplugins/python/ngl_line_plugin.py
ngl_utils/nplugins/python/ngl_rect_plugin.py
ngl_utils/nplugins/python/ngl_seekbar_plugin.py
ngl_utils/nplugins/python/ico/button.ico
ngl_utils/nplugins/python/ico/line.ico
ngl_utils/nplugins/python/ico/rect.ico
ngl_utils/nplugins/widgets/__init__.py
ngl_utils/nplugins/widgets/ngl_base.py
ngl_utils/nplugins/widgets/ngl_bitmap.py
ngl_utils/nplugins/widgets/ngl_button.py
ngl_utils/nplugins/widgets/ngl_checkbox.py
ngl_utils/nplugins/widgets/ngl_colors.py
ngl_utils/nplugins/widgets/ngl_fillbar.py
ngl_utils/nplugins/widgets/ngl_graph_scale.py
ngl_utils/nplugins/widgets/ngl_label.py
ngl_utils/nplugins/widgets/ngl_line.py
ngl_utils/nplugins/widgets/ngl_rect.py
ngl_utils/nplugins/widgets/ngl_seekbar.py
ngl_utils/nplugins/widgets/qstyle_parser.py
ngl_utils/templates/bitmap.ntp
ngl_utils/templates/button.ntp
ngl_utils/templates/checkbox.ntp
ngl_utils/templates/fillbar.ntp
ngl_utils/templates/font.ntp
ngl_utils/templates/function.ntp
