Metadata-Version: 1.1
Name: ngl-utils
Version: 1.4.9
Summary: ngl_utils converting/generate code utilities for embedded NGL library
Home-page: https://github.com/LeftRadio/ngl_utils
Author: Vladislav Kamenev
Author-email: wladkam@mail.com
License: MIT
Download-URL: https://github.com/LeftRadio/ngl_utils
Platform: UNKNOWN
Classifier: Development Status :: 4 - Beta
Classifier: Programming Language :: Python :: 3
